LICENCE.txt
MANIFEST.in
README.txt
setup.py
SenCalculator/__init__.py
SenCalculator.egg-info/PKG-INFO
SenCalculator.egg-info/SOURCES.txt
SenCalculator.egg-info/dependency_links.txt
SenCalculator.egg-info/top_level.txt